LICENSE
README.md
setup.py
trendpy2/__init__.py
trendpy2/methods.py
trendpy2/models.py
trendpy2/webApp.py
trendpy2.egg-info/PKG-INFO
trendpy2.egg-info/SOURCES.txt
trendpy2.egg-info/dependency_links.txt
trendpy2.egg-info/requires.txt
trendpy2.egg-info/top_level.txt