Metadata-Version: 2.1
Name: trendpy2
Version: 1.0.2
Summary: Time series regression with python
Home-page: https://github.com/zolabar/trendPy/tree/main
Author: Zoufiné Lauer-Baré
License: MIT License
License-File: LICENSE
